cvx/cli/__init__.py
cvx/cli/smallest_eigenvalue.py
cvx/cli/weather.py
cvxcli-0.1.0.dist-info/METADATA
cvxcli-0.1.0.dist-info/WHEEL
cvxcli-0.1.0.dist-info/entry_points.txt
cvxcli-0.1.0.dist-info/licenses/LICENSE
cvxcli-0.1.0.dist-info/RECORD
