Metadata-Version: 2.4
Name: cvxcli
Version: 0.1.0
Summary: Simple command line app demo
Project-URL: repository, https://github.com/cvxgrp/cvxcli
Author-email: Thomas Schmelzer <thomas.schmelzer@gmail.com>
License-File: LICENSE
Requires-Python: >=3.10
Requires-Dist: cvxbson>=0.1.0
Requires-Dist: fire>=0.7.0
Requires-Dist: numpy>=2.2.1
Requires-Dist: requests>=2.32.3
